botowrap/__init__.py
botowrap/core.py
botowrap/py.typed
botowrap/extensions/__init__.py
botowrap/extensions/dynamodb.py
botowrap/types/__init__.py
botowrap/types/core.pyi
botowrap/types/extensions/__init__.py
botowrap/types/extensions/dynamodb.pyi
botowrap-0.1.1.dist-info/licenses/LICENSE
botowrap-0.1.1.dist-info/METADATA
botowrap-0.1.1.dist-info/WHEEL
botowrap-0.1.1.dist-info/top_level.txt
botowrap-0.1.1.dist-info/RECORD
